slide_stream/__init__.py
slide_stream/cli.py
slide_stream/config.py
slide_stream/config_loader.py
slide_stream/llm.py
slide_stream/media.py
slide_stream/parser.py
slide_stream/powerpoint.py
slide_stream/providers/__init__.py
slide_stream/providers/base.py
slide_stream/providers/factory.py
slide_stream/providers/images.py
slide_stream/providers/tts.py
slide_stream-2.0.0.dist-info/METADATA
slide_stream-2.0.0.dist-info/WHEEL
slide_stream-2.0.0.dist-info/entry_points.txt
slide_stream-2.0.0.dist-info/licenses/LICENSE
slide_stream-2.0.0.dist-info/RECORD
