Metadata-Version: 2.4
Name: slide-stream
Version: 2.0.0
Summary: An AI-powered tool to automatically create video presentations from Markdown and PowerPoint files
Project-URL: Homepage, https://github.com/yourusername/slide-stream
Project-URL: Repository, https://github.com/yourusername/slide-stream
Project-URL: Issues, https://github.com/yourusername/slide-stream/issues
Author-email: Your Name <your.email@example.com>
License: MIT
License-File: LICENSE
Keywords: ai,cli,markdown,presentation,video
Classifier: Development Status :: 4 - Beta
Classifier: Environment :: Console
Classifier: Intended Audience :: Developers
Classifier: Intended Audience :: End Users/Desktop
Classifier: License :: OSI Approved :: MIT License
Classifier: Operating System :: OS Independent
Classifier: Programming Language :: Python :: 3
Classifier: Programming Language :: Python :: 3.10
Classifier: Programming Language :: Python :: 3.11
Classifier: Programming Language :: Python :: 3.12
Classifier: Topic :: Multimedia :: Video
Classifier: Topic :: Text Processing :: Markup
Requires-Python: >=3.10
Requires-Dist: anthropic>=0.7.0; extra == 'claude'
Requires-Dist: beautifulsoup4>=4.12.0
Requires-Dist: elevenlabs>=1.0.0; extra == 'elevenlabs'
Requires-Dist: google-generativeai>=0.3.0; extra == 'gemini'
Requires-Dist: groq>=0.4.0; extra == 'groq'
Requires-Dist: gtts>=2.4.0
Requires-Dist: markdown>=3.5.0
Requires-Dist: moviepy>=1.0.3
Requires-Dist: openai>=1.0.0; extra == 'openai'
Requires-Dist: pillow>=10.0.0
Requires-Dist: python-pptx>=1.0.2
Requires-Dist: pyyaml>=6.0.0
Requires-Dist: requests>=2.31.0
Requires-Dist: rich>=13.0.0
Requires-Dist: typer>=0.9.0
Requires-Dist: typing-extensions>=4.8.0
Provides-Extra: all-ai
Requires-Dist: anthropic>=0.7.0; extra == 'all-ai'
Requires-Dist: elevenlabs>=1.0.0; extra == 'all-ai'
Requires-Dist: google-generativeai>=0.3.0; extra == 'all-ai'
Requires-Dist: groq>=0.4.0; extra == 'all-ai'
Requires-Dist: openai>=1.0.0; extra == 'all-ai'
Provides-Extra: claude
Requires-Dist: anthropic>=0.7.0; extra == 'claude'
Provides-Extra: dev
Requires-Dist: basedpyright>=1.8.0; extra == 'dev'
Requires-Dist: pre-commit>=3.5.0; extra == 'dev'
Requires-Dist: pytest-cov>=4.1.0; extra == 'dev'
Requires-Dist: pytest-mock>=3.12.0; extra == 'dev'
Requires-Dist: pytest>=7.4.0; extra == 'dev'
Requires-Dist: ruff>=0.1.0; extra == 'dev'
Provides-Extra: elevenlabs
Requires-Dist: elevenlabs>=1.0.0; extra == 'elevenlabs'
Provides-Extra: gemini
Requires-Dist: google-generativeai>=0.3.0; extra == 'gemini'
Provides-Extra: groq
Requires-Dist: groq>=0.4.0; extra == 'groq'
Provides-Extra: openai
Requires-Dist: openai>=1.0.0; extra == 'openai'
